_cubrid.cpython-313t-x86_64-linux-gnu.so
cubrid_db/__init__.py
cubrid_db/connections.py
cubrid_db/cursors.py
cubrid_db/exceptions.py
cubrid_db/field_type.py
cubrid_db-0.7.1.dist-info/AUTHORS
cubrid_db-0.7.1.dist-info/LICENSE
cubrid_db-0.7.1.dist-info/METADATA
cubrid_db-0.7.1.dist-info/WHEEL
cubrid_db-0.7.1.dist-info/top_level.txt
cubrid_db-0.7.1.dist-info/RECORD
