Metadata-Version: 2.2
Name: cubrid_db
Version: 0.7.1
Summary: Python interface to CUBRID
Home-page: https://github.com/zimbrul-co/cubrid_db
Author: Casian Andrei
Author-email: casian@zco.ro
License: BSD
License-File: LICENSE
License-File: AUTHORS
Dynamic: author
Dynamic: author-email
Dynamic: description
Dynamic: description-content-type
Dynamic: home-page
Dynamic: license
Dynamic: summary
